usbfan
