Metadata-Version: 2.1
Name: microwave-usbfan
Version: 1.1
Summary: Implementation of the Jaycar RGB USB LED fan (GH1031) protocol
Home-page: https://github.com/fergofrog/microwave_usb_fan
Author: Fergus Symon
Author-email: 45412+fergofrog@users.noreply.github.com
License: MIT
Platform: UNKNOWN
Classifier: Development Status :: 5 - Production/Stable
Classifier: Intended Audience :: Information Technology
Classifier: License :: OSI Approved :: Apache Software License
Classifier: Operating System :: MacOS
Classifier: Operating System :: Microsoft :: Windows
Classifier: Operating System :: POSIX :: BSD
Classifier: Operating System :: POSIX :: Linux
Classifier: Programming Language :: Python :: 3.6
Classifier: Programming Language :: Python :: 3.7
Classifier: Topic :: Communications
Classifier: Topic :: Software Development :: Libraries :: Python Modules
